{"content":[{"id":"2f7bf546","settings":{"layout":"full_width","height":"min-height","custom_height":{"unit":"px","size":700,"sizes":[]},"overflow":"hidden","background_background":"gradient","background_image":{"url":"https:\/\/datasecret.com.br\/wp-content\/uploads\/2021\/10\/network-4851079_1920.jpg","id":403,"alt":"","source":"library"},"background_repeat":"no-repeat","background_size":"cover","background_color":"#20183D","background_color_b":"#20183D"},"elements":[{"id":"24a03023","settings":{"_column_size":100,"_inline_size":100,"align":"center"},"elements":[{"id":"95cfe29","settings":{"title":"","header_size":"h1","title_color":"#FFFFFF","typography_typography":"custom","_padding":{"unit":"px","top":"0","right":"0","bottom":"0","left":"0","isLinked":false}},"elements":[],"isInner":false,"widgetType":"heading","elType":"widget"},{"id":"268dc54b","settings":{"structure":"20"},"elements":[{"id":"329cb90f","settings":{"_column_size":50,"_inline_size":61.31400000000000005684341886080801486968994140625},"elements":[{"id":"1bed0a11","settings":{"title":"<h1 class=\"elementor-heading-title elementor-size-default elementor-inline-editing pen\" data-elementor-setting-key=\"title\" data-pen-placeholder=\"Digite aqui...\" style=\"font-size: 3.2rem; font-style: normal; color: rgb(255, 255, 255);\"><b>Solu\u00e7\u00f5es em privacidade <br>e prote\u00e7\u00e3o de dados<\/b><\/h1>","_background_background":"classic","_background_color":"#20183D","align":"left","typography_typography":"custom","typography_font_size":{"unit":"px","size":1,"sizes":[]},"_margin":{"unit":"px","top":"30","right":"015","bottom":"30","left":"015","isLinked":false},"text_shadow_text_shadow_type":"yes","text_shadow_text_shadow":{"horizontal":0,"vertical":0,"blur":10,"color":"rgba(255, 251.1195652173913, 251.1195652173913, 0.62)"}},"elements":[],"isInner":false,"widgetType":"heading","elType":"widget"}],"isInner":true,"elType":"column"},{"id":"179d9944","settings":{"_column_size":50,"_inline_size":38.64200000000000301270119962282478809356689453125},"elements":[{"id":"4aad15bd","settings":{"image":{"url":"https:\/\/datasecret.com.br\/wp-content\/uploads\/2021\/10\/security_PNG.png","id":427,"alt":"","source":"library"},"hide_mobile":"hidden-mobile","align":"left","image_box_shadow_box_shadow_type":"yes","image_box_shadow_box_shadow":{"horizontal":0,"vertical":0,"blur":10,"spread":0,"color":"rgba(255, 255, 255, 0)"}},"elements":[],"isInner":false,"widgetType":"image","elType":"widget"}],"isInner":true,"elType":"column"}],"isInner":true,"elType":"section"}],"isInner":false,"elType":"column"}],"isInner":false,"elType":"section"},{"id":"7d1da8c8","settings":[],"elements":[{"id":"45375f7d","settings":{"_column_size":100,"_inline_size":null},"elements":[{"id":"77f36055","settings":{"title":"<b>Servi\u00e7os<\/b>","align":"center","_margin":{"unit":"px","top":"030","right":"0","bottom":"015","left":"0","isLinked":false},"title_color":"#20183D","typography_typography":"custom","typography_font_weight":"700","typography_text_transform":"uppercase"},"elements":[],"isInner":false,"widgetType":"heading","elType":"widget"}],"isInner":false,"elType":"column"}],"isInner":false,"elType":"section"},{"id":"3e0804bc","settings":{"structure":"30"},"elements":[{"id":"487d51e1","settings":{"_column_size":33,"_inline_size":null},"elements":[{"id":"1579725c","settings":{"image":{"url":"https:\/\/datasecret.com.br\/wp-content\/uploads\/2021\/10\/1470399662_Marketing.png","id":322,"alt":"","source":"library"},"title_text":"Treinamento","description_text":"Conscientiza\u00e7\u00e3o e capacita\u00e7\u00e3o sobre os principais conceitos, princ\u00edpios, diretrizes e obriga\u00e7\u00f5es previstas na LGPD.","_padding":{"unit":"em","top":"04","right":"1","bottom":"4","left":"1","isLinked":false},"_css_classes":"card-datasecret","_box_shadow_box_shadow_type":"yes","_box_shadow_box_shadow":{"horizontal":0,"vertical":0,"blur":20,"spread":0,"color":"rgba(0,0,0,0.5)"},"css_filters_css_filter":"custom","title_color":"#FFFFFF","description_color":"#FFFFFF","_background_hover_color":"#FFFFFF","position":"left","title_typography_typography":"custom","title_typography_font_weight":"700"},"elements":[],"isInner":false,"widgetType":"image-box","elType":"widget"}],"isInner":false,"elType":"column"},{"id":"53ade8c7","settings":{"_column_size":33,"_inline_size":null},"elements":[{"id":"73dac446","settings":{"image":{"url":"https:\/\/datasecret.com.br\/wp-content\/uploads\/2021\/10\/1470399607_Illustration-1.png","id":319,"alt":"","source":"library"},"title_text":"Implementa\u00e7\u00e3o","description_text":"Projeto de implementa\u00e7\u00e3o que promove a adequa\u00e7\u00e3o com a LGPD a partir de um programa amplo de conformidade.","_padding":{"unit":"em","top":"04","right":"1","bottom":"4","left":"1","isLinked":false},"_css_classes":"card-datasecret","_box_shadow_box_shadow_type":"yes","_box_shadow_box_shadow":{"horizontal":0,"vertical":0,"blur":20,"spread":0,"color":"rgba(0,0,0,0.5)"},"position":"left","_background_background":"gradient","title_color":"#FFFFFF","title_typography_typography":"custom","title_typography_font_weight":"700","description_color":"#FFFFFF"},"elements":[],"isInner":false,"widgetType":"image-box","elType":"widget"}],"isInner":false,"elType":"column"},{"id":"4e9c0e59","settings":{"_column_size":33,"_inline_size":null},"elements":[{"id":"75217375","settings":{"image":{"url":"https:\/\/datasecret.com.br\/wp-content\/uploads\/2021\/10\/1470399674_App_Development-1.png","id":327,"alt":"","source":"library"},"title_text":"Auditoria","description_text":"Verifica\u00e7\u00e3o e valida\u00e7\u00e3o do programa de prote\u00e7\u00e3o de dados pessoais j\u00e1 existente na organiza\u00e7\u00e3o","_padding":{"unit":"em","top":"04","right":"1","bottom":"04","left":"1","isLinked":false},"_css_classes":"card-datasecret","_box_shadow_box_shadow_type":"yes","_box_shadow_box_shadow":{"horizontal":0,"vertical":0,"blur":20,"spread":0,"color":"rgba(0,0,0,0.5)"},"position":"left","title_color":"#FFFFFF","title_typography_typography":"custom","title_typography_font_weight":"700","description_color":"#FFFFFF"},"elements":[],"isInner":false,"widgetType":"image-box","elType":"widget"}],"isInner":false,"elType":"column"}],"isInner":false,"elType":"section"},{"id":"7a86d6f7","settings":{"structure":"21"},"elements":[{"id":"1d3196a9","settings":{"_column_size":33,"_inline_size":52.893000000000000682121026329696178436279296875},"elements":[{"id":"2e49751a","settings":{"image":{"url":"https:\/\/datasecret.com.br\/wp-content\/uploads\/2021\/10\/1470399671_SEO.png","id":323,"alt":"","source":"library"},"title_text":"DPO as a Service","description_text":"Nomea\u00e7\u00e3o da Data Secret como encarregado de dados (DPO) da organiza\u00e7\u00e3o.","position":"left","_padding":{"unit":"em","top":"4","right":"1","bottom":"4","left":"1","isLinked":false},"_css_classes":"card-datasecret","_background_color":"#FFFFFF","_box_shadow_box_shadow_type":"yes","_box_shadow_box_shadow":{"horizontal":0,"vertical":0,"blur":20,"spread":0,"color":"rgba(0,0,0,0.5)"},"title_color":"#FFFFFF","title_typography_typography":"custom","title_typography_font_weight":"700","description_color":"#FFFFFF"},"elements":[],"isInner":false,"widgetType":"image-box","elType":"widget"}],"isInner":false,"elType":"column"},{"id":"5864f5a1","settings":{"_column_size":66,"_inline_size":46.71600000000000108002495835535228252410888671875},"elements":[{"id":"1156c9b8","settings":{"image":{"url":"https:\/\/datasecret.com.br\/wp-content\/uploads\/2021\/10\/1470399715_E-Commerce.png","id":324,"alt":"","source":"library"},"title_text":"Opera\u00e7\u00e3o Assistida ao DPO","description_text":"Lorem ipsum dolor sit amet, consectetur adipiscing elit. Ut elit tellus, luctus nec ullamcorper mattis, pulvinar dapibus leo.","position":"left","_padding":{"unit":"em","top":"04","right":"1","bottom":"4","left":"1","isLinked":false},"_css_classes":"card-datasecret","_box_shadow_box_shadow_type":"yes","_box_shadow_box_shadow":{"horizontal":0,"vertical":0,"blur":20,"spread":0,"color":"rgba(0,0,0,0.5)"},"custom_css":".card-datasecret{\n    min-height: 260px;\n    background: linear-gradient(\n149deg, rgba(32,24,61,1) 0%, rgba(45,139,191,1) 100%, rgba(252,70,107,1) 100%);\n}\n.card-datasecret .elementor-widget-container{\n    height: 100%\n}\n\n.card-datasecret .elementor-widget-container img{\n    filter: brightness( 0% ) invert(1) !important;\n}","title_color":"#FFFFFF","title_typography_typography":"custom","title_typography_font_weight":"700","description_color":"#FFFFFF"},"elements":[],"isInner":false,"widgetType":"image-box","elType":"widget"}],"isInner":false,"elType":"column"}],"isInner":false,"elType":"section"},{"id":"5ee50c9d","settings":[],"elements":[{"id":"2e494d0b","settings":{"_column_size":100,"_inline_size":null},"elements":[{"id":"c7824e9","settings":{"title":"<b>Parceiros<\/b>","align":"center","_margin":{"unit":"px","top":"030","right":"00","bottom":"15","left":"0","isLinked":false},"_padding":{"unit":"px","top":"0","right":"0","bottom":"0","left":"0","isLinked":false},"title_color":"#20183D","typography_typography":"custom","typography_font_weight":"700","typography_text_transform":"uppercase"},"elements":[],"isInner":false,"widgetType":"heading","elType":"widget"}],"isInner":false,"elType":"column"}],"isInner":false,"elType":"section"},{"id":"760a160d","settings":[],"elements":[{"id":"7e9d52dd","settings":{"_column_size":100,"_inline_size":null},"elements":[{"id":"79d68284","settings":{"carousel":[{"id":499,"url":"https:\/\/datasecret.com.br\/wp-content\/uploads\/2021\/10\/g2.png"},{"id":500,"url":"https:\/\/datasecret.com.br\/wp-content\/uploads\/2021\/10\/multigiro-removebg-preview.png"},{"id":501,"url":"https:\/\/datasecret.com.br\/wp-content\/uploads\/2021\/10\/salesiano-removebg-preview.png"}],"slides_to_show":"3","slides_to_scroll":"3","dots_position":"inside","gallery_vertical_align":"center","thumbnail_size":"custom","thumbnail_custom_dimension":{"width":"200","height":""},"dots_color":"#FFFFFF"},"elements":[],"isInner":false,"widgetType":"image-carousel","elType":"widget"},{"id":"565e6a26","settings":{"title":"Contato","align":"center","typography_typography":"custom","typography_font_weight":"700","_margin":{"unit":"px","top":"30","right":"00","bottom":"15","left":"0","isLinked":false},"_background_background":"classic","_background_color":"#FFFFFF","title_color":"#20183D","typography_text_transform":"uppercase"},"elements":[],"isInner":false,"widgetType":"heading","elType":"widget"}],"isInner":false,"elType":"column"}],"isInner":false,"elType":"section"},{"id":"7cd18f3e","settings":{"structure":"31"},"elements":[{"id":"7d6e7df1","settings":{"_column_size":25,"_inline_size":47.63000000000000255795384873636066913604736328125},"elements":[{"id":"2a7610bd","settings":{"structure":"20","css_classes":"box-icon-text"},"elements":[{"id":"e1683c6","settings":{"_column_size":50,"_inline_size":16.9200000000000017053025658242404460906982421875},"elements":[{"id":"1b600180","settings":{"selected_icon":{"value":"fab fa-whatsapp","library":"fa-brands"},"primary_color":"#20183D","custom_css":".box-icon-text{\n    flex-direction: row;\n}"},"elements":[],"isInner":false,"widgetType":"icon","elType":"widget"}],"isInner":true,"elType":"column"},{"id":"6d382804","settings":{"_column_size":50,"_inline_size":83.0799999999999982946974341757595539093017578125},"elements":[{"id":"7ea38e5d","settings":{"title":"(84) 98777-4076","align":"left","typography_typography":"custom","_margin":{"unit":"px","top":"05","right":"0","bottom":"0","left":"0","isLinked":false},"title_color":"#20183D","align_mobile":"center"},"elements":[],"isInner":false,"widgetType":"heading","elType":"widget"}],"isInner":true,"elType":"column"}],"isInner":true,"elType":"section"},{"id":"22007708","settings":{"structure":"20","css_classes":"box-icon-text"},"elements":[{"id":"4e08734c","settings":{"_column_size":50,"_inline_size":16.9200000000000017053025658242404460906982421875},"elements":[{"id":"4c78c809","settings":{"selected_icon":{"value":"fab fa-instagram","library":"fa-brands"},"primary_color":"#20183D"},"elements":[],"isInner":false,"widgetType":"icon","elType":"widget"}],"isInner":true,"elType":"column"},{"id":"3bc5f0e2","settings":{"_column_size":50,"_inline_size":83.0799999999999982946974341757595539093017578125},"elements":[{"id":"c87ed32","settings":{"title":"@datasecret.br","align":"left","typography_typography":"custom","_margin":{"unit":"px","top":"05","right":"0","bottom":"0","left":"0","isLinked":false},"link":{"url":"https:\/\/www.instagram.com\/datasecret.br\/","is_external":"","nofollow":"","custom_attributes":""},"title_color":"#20183D","align_mobile":"center"},"elements":[],"isInner":false,"widgetType":"heading","elType":"widget"}],"isInner":true,"elType":"column"}],"isInner":true,"elType":"section"},{"id":"101443df","settings":{"structure":"20","css_classes":"box-icon-text"},"elements":[{"id":"70219f64","settings":{"_column_size":50,"_inline_size":16.9200000000000017053025658242404460906982421875},"elements":[{"id":"4330d8c6","settings":{"selected_icon":{"value":"far fa-envelope","library":"fa-regular"},"primary_color":"#20183D","_css_classes":"box-icon-text"},"elements":[],"isInner":false,"widgetType":"icon","elType":"widget"}],"isInner":true,"elType":"column"},{"id":"555c2c8d","settings":{"_column_size":50,"_inline_size":83.0799999999999982946974341757595539093017578125},"elements":[{"id":"14581641","settings":{"title":"contato@datasecret.com.br","align":"left","typography_typography":"custom","_margin":{"unit":"px","top":"5","right":"0","bottom":"0","left":"0","isLinked":false},"__dynamic__":[],"align_mobile":"center"},"elements":[],"isInner":false,"widgetType":"heading","elType":"widget"}],"isInner":true,"elType":"column"}],"isInner":true,"elType":"section"}],"isInner":false,"elType":"column"},{"id":"77f2c51d","settings":{"_column_size":25,"_inline_size":2.37000000000000010658141036401502788066864013671875},"elements":[],"isInner":false,"elType":"column"},{"id":"3849d8a","settings":{"_column_size":50,"_inline_size":null},"elements":[{"id":"44c84e29","settings":{"shortcode":"[wpforms id=\"204\"]"},"elements":[],"isInner":false,"widgetType":"shortcode","elType":"widget"}],"isInner":false,"elType":"column"}],"isInner":false,"elType":"section"}],"page_settings":[],"version":"0.4","title":"P\u00e1gina Inicial","type":"page"}